pycache_handler/__init__.py
pycache_handler/handler.py
pycache_handler-0.1.7.dist-info/LICENSE.md
pycache_handler-0.1.7.dist-info/METADATA
pycache_handler-0.1.7.dist-info/WHEEL
pycache_handler-0.1.7.dist-info/top_level.txt
pycache_handler-0.1.7.dist-info/RECORD
