Metadata-Version: 2.1
Name: pycache_handler
Version: 0.1.7
Summary: Python package to automatically delete __pycache__ directories.
Home-page: https://github.com/iv4n-ga6l/pycache_handler
Author: Ivan APEDO
Author-email: apedoivan@gmail.com
Classifier: Programming Language :: Python :: 3
Classifier: License :: OSI Approved :: MIT License
Classifier: Operating System :: OS Independent
Requires-Python: >=3.6
License-File: LICENSE.md
Requires-Dist: watchdog
